{
  "id": "giac.gcfr",
  "vendor": {
    "slug": "giac",
    "name": "GIAC",
    "url": "https://www.giac.org/"
  },
  "name": "GIAC Cloud Forensics Responder",
  "abbr": "GCFR",
  "domain": "incident-forensics",
  "secondary_domains": [
    "cloud-security"
  ],
  "japan_only": false,
  "official": {
    "exam_url": "https://www.giac.org/certifications/cloud-forensics-responder-gcfr/",
    "fetched_at": "2026-05-02"
  },
  "logistics": {
    "cost_usd": 999,
    "format": "Web-based proctored, open-book reference (ProctorU or PearsonVUE)",
    "duration_min": 180,
    "questions": 82,
    "languages": [
      "en"
    ],
    "renewal_years": 4,
    "ce_required": true
  },
  "prerequisites": {
    "formal": [],
    "experience_years": 3,
    "recommended_certs": [
      {
        "id": "giac.gcfa",
        "source": "vendor-ladder",
        "rationale": "GCFA でオンプレ DFIR の基礎を持ったうえで、AWS/Azure/M365 のクラウド調査を評価する GCFR に進むと現代 DFIR の網羅性が高まる。"
      },
      {
        "id": "giac.gcih",
        "source": "vendor-ladder"
      },
      {
        "id": "giac.gcld",
        "source": "vendor-ladder"
      },
      {
        "id": "giac.geir",
        "source": "vendor-ladder"
      },
      {
        "id": "giac.gsoc",
        "source": "vendor-ladder"
      }
    ]
  },
  "scoring_factors": {
    "plus": [
      {
        "code": "ANSI_ISO_17024_ACCREDITED",
        "weight_hint": "high"
      },
      {
        "code": "CLOUD_FORENSICS_NICHE",
        "weight_hint": "high",
        "note": "クラウドログ/コントロールプレーン中心の DFIR 認証は希少で、現代 SOC/CSIRT に直結。"
      },
      {
        "code": "BACKED_BY_SANS_TRAINING",
        "weight_hint": "medium"
      }
    ],
    "minus": [
      {
        "code": "EXPENSIVE_BUNDLE",
        "weight_hint": "high"
      },
      {
        "code": "OPEN_BOOK_FORMAT",
        "weight_hint": "low"
      }
    ]
  },
  "third_party_evaluations": [
    {
      "source_id": "ansi-iso-17024",
      "level_hint": "professional",
      "url": "https://www.ansica.org/wwwversion2/outside/PERdirectoryListing.asp",
      "fetched_at": "2026-05-02"
    }
  ],
  "sources": [
    {
      "type": "official",
      "url": "https://www.giac.org/certifications/cloud-forensics-responder-gcfr/"
    },
    {
      "type": "third_party",
      "url": "https://www.sans.org/cyber-security-courses/enterprise-cloud-forensics-incident-response/"
    }
  ],
  "evaluation": {
    "computed_tier": "professional",
    "computed_at": "2026-05-02T14:04:04Z",
    "computed_by_skill": "evaluate-roadmap-3-personas@1",
    "rationale": "All three personas agree at this tier; rationale reflects consensus.",
    "persona_scores": {
      "hiroshi-tanaka": {
        "tier": "professional",
        "rationale": "Auto-derived from third-party evaluations (professional); pending differentiated human persona review."
      },
      "maria-okonkwo": {
        "tier": "professional",
        "rationale": "Auto-derived from third-party evaluations (professional); pending differentiated human persona review."
      },
      "alex-novak": {
        "tier": "professional",
        "rationale": "Auto-derived from third-party evaluations (professional); pending differentiated human persona review."
      }
    }
  },
  "schema_version": 1
}
